stockutilitiesqnp/__init__.py
stockutilitiesqnp/market-hours-data.json
stockutilitiesqnp/market_hours.py
stockutilitiesqnp/timing.py
stockutilitiesqnp-0.1.0.dist-info/METADATA
stockutilitiesqnp-0.1.0.dist-info/WHEEL
stockutilitiesqnp-0.1.0.dist-info/top_level.txt
stockutilitiesqnp-0.1.0.dist-info/RECORD
