Metadata-Version: 2.1
Name: stockutilitiesqnp
Version: 0.1.0
Summary: UNKNOWN
Home-page: UNKNOWN
License: UNKNOWN
Platform: UNKNOWN
Requires-Dist: python-dateutil (==2.8.1)
